observe_http_sender.py
observe_http_sender-1.3.3.dist-info/LICENSE
observe_http_sender-1.3.3.dist-info/METADATA
observe_http_sender-1.3.3.dist-info/WHEEL
observe_http_sender-1.3.3.dist-info/top_level.txt
observe_http_sender-1.3.3.dist-info/RECORD
