Metadata-Version: 2.1
Name: observe-http-sender
Version: 1.3.3
Summary: A Python class to send events to an Observe Inc Datastream via the HTTP API endpoint
Home-page: https://github.com/observeinc/observe-http-sender-python
Download-URL: https://github.com/observeinc/observe-http-sender-python/archive/refs/heads/main.zip
Author: Observe Inc
Author-email: Observe Inc <devinfra@observeinc.com>
Project-URL: Homepage, https://github.com/observeinc/observe-http-sender-python
Project-URL: Issues, https://github.com/observeinc/observe-http-sender-python/issues
Keywords: observeinc,http,ingest
Classifier: Programming Language :: Python :: 3.7
Classifier: License :: OSI Approved :: Apache Software License
Classifier: Operating System :: OS Independent
Classifier: Development Status :: 5 - Production/Stable
Classifier: Intended Audience :: Developers
Classifier: Framework :: AsyncIO
Classifier: Topic :: Scientific/Engineering
Classifier: Topic :: Scientific/Engineering :: Information Analysis
Classifier: Topic :: Software Development :: Libraries :: Python Modules
Requires-Python: >=3.7
License-File: LICENSE
Requires-Dist: asyncio
Requires-Dist: aiohttp
Requires-Dist: aiohttp-retry
